drf_model_pusher/__init__.py
drf_model_pusher/backends.py
drf_model_pusher/config.py
drf_model_pusher/exceptions.py
drf_model_pusher/receivers.py
drf_model_pusher/signals.py
drf_model_pusher/views.py
drf_model_pusher-0.1.1.dist-info/METADATA
drf_model_pusher-0.1.1.dist-info/RECORD
drf_model_pusher-0.1.1.dist-info/WHEEL
drf_model_pusher-0.1.1.dist-info/top_level.txt
