Metadata-Version: 2.1
Name: drf-model-pusher
Version: 0.1.1
Summary: Easy to use class mixins for Django Rest Framework and Pusher to keep your API realtime.
Home-page: https://github.com/aljp/drf_model_pusher
Author: Adam Jacquier-Parr
Author-email: aljparr0@gmail.com
License: MIT
Platform: UNKNOWN
Classifier: License :: OSI Approved :: MIT License
Classifier: Programming Language :: Python
Classifier: Programming Language :: Python :: 3
Classifier: Programming Language :: Python :: 3.6
Classifier: Programming Language :: Python :: Implementation :: CPython
Classifier: Programming Language :: Python :: Implementation :: PyPy
Requires-Python: >=3.6.0
Requires-Dist: django
Requires-Dist: djangorestframework
Requires-Dist: pusher
